schemachange/JinjaEnvVar.py
schemachange/JinjaTemplateProcessor.py
schemachange/__init__.py
schemachange/cli.py
schemachange/deploy.py
schemachange/py.typed
schemachange/redact_config_secrets.py
schemachange/config/BaseConfig.py
schemachange/config/ChangeHistoryTable.py
schemachange/config/DeployConfig.py
schemachange/config/RenderConfig.py
schemachange/config/VerifyConfig.py
schemachange/config/__init__.py
schemachange/config/get_merged_config.py
schemachange/config/parse_cli_args.py
schemachange/config/utils.py
schemachange/session/Credential.py
schemachange/session/Script.py
schemachange/session/SnowflakeSession.py
schemachange/session/__init__.py
schemachange-4.1.0.dist-info/METADATA
schemachange-4.1.0.dist-info/WHEEL
schemachange-4.1.0.dist-info/entry_points.txt
schemachange-4.1.0.dist-info/licenses/LICENSE
schemachange-4.1.0.dist-info/licenses/NOTICE
schemachange-4.1.0.dist-info/RECORD
