Metadata-Version: 2.4
Name: schemachange
Version: 4.1.0
Summary: A Database Change Management tool for Snowflake
Project-URL: Homepage, https://github.com/Snowflake-Labs/schemachange
Project-URL: Repository, https://github.com/Snowflake-Labs/schemachange
Author: jamesweakley/jeremiahhansen
License: Apache-2.0
License-File: LICENSE
License-File: NOTICE
Classifier: License :: OSI Approved :: Apache Software License
Classifier: Operating System :: OS Independent
Classifier: Programming Language :: Python :: 3
Classifier: Programming Language :: Python :: 3 :: Only
Classifier: Programming Language :: Python :: 3.10
Classifier: Programming Language :: Python :: 3.11
Classifier: Programming Language :: Python :: 3.12
Classifier: Programming Language :: Python :: 3.13
Requires-Python: >=3.10
Requires-Dist: cryptography
Requires-Dist: jinja2~=3.0
Requires-Dist: pyyaml~=6.0
Requires-Dist: requests
Requires-Dist: snowflake-connector-python<5.0,>=2.8
Requires-Dist: structlog~=24.1.0
Provides-Extra: dev
Requires-Dist: black; extra == 'dev'
Requires-Dist: flake8; extra == 'dev'
Requires-Dist: pre-commit; extra == 'dev'
Requires-Dist: pyfakefs; extra == 'dev'
Requires-Dist: pytest; extra == 'dev'
Requires-Dist: ruff; extra == 'dev'
